[
    {
        "id" : 1,
        "image" : "./assets/images/kimcry1.png"
    },
    {
        "id" : 2,
        "image" : "./assets/images/kimcry2.png"
    },
    {
        "id" : 3,
        "image" : "./assets/images/kimcry3.png"
    },
    {
        "id" : 4,
        "image" : "./assets/images/kimcry4.png"
    },
    {
        "id" : 5,
        "image" : "./assets/images/kimcry5.png"
    },
    {
        "id" : 6,
        "image" : "./assets/images/kimcry6.png"
    },
    {
        "id" : 7,
        "image" : "./assets/images/kimcry7.png"
    },
    {
        "id" : 8,
        "image" : "./assets/images/kimcry8.png"
    },
    {
        "id" : 9,
        "image" : "./assets/images/kimcry9.png"
    },
    {
        "id" : 10,
        "image" : "./assets/images/kimcry10.png"
    }
]